Metadata-Version: 1.1
Name: crisps
Version: 0.0.3.1
Summary: Eat and get fat.
Home-page: UNKNOWN
Author: IYEIds
Author-email: yigidogulay@gmail.com
License: MIT
Keywords: crisps,fat,chabby,eat
Platform: UNKNOWN
Classifier: Development Status :: 5 - Production/Stable
Classifier: Intended Audience :: Education
Classifier: Operating System :: Microsoft :: Windows :: Windows 10
Classifier: License :: OSI Approved :: MIT License
Classifier: Programming Language :: Python :: 3
